PIModelManager/__init__.py
PIModelManager/logging/logging.conf
PIModelManager/model_manager.py
PIModelManager/model_manager_test.py
PIModelManager/pandora_model.py
pimodelmanager-0.8.3.dist-info/WHEEL
pimodelmanager-0.8.3.dist-info/METADATA
pimodelmanager-0.8.3.dist-info/RECORD
