Metadata-Version: 2.1
Name: pimodelmanager
Version: 0.8.3
Summary: A package used to manage our ML models.
License: Pandora Intelligence
Author: Martin Kirilov
Requires-Python: >=3.8,<4.0
Classifier: License :: Other/Proprietary License
Classifier: Programming Language :: Python :: 3
Classifier: Programming Language :: Python :: 3.10
Classifier: Programming Language :: Python :: 3.8
Classifier: Programming Language :: Python :: 3.9
Requires-Dist: aioify (>=0.4.0,<0.5.0)
Requires-Dist: ray[serve] (>=1.7.1,<2.0.0)
Requires-Dist: requests (>=2.25.1,<3.0.0)
